{
    "Function": "brcmf_mp_attach",
    "astEdges": [
        [
            23,
            24
        ],
        [
            12,
            16
        ],
        [
            12,
            13
        ],
        [
            4,
            6
        ],
        [
            4,
            5
        ],
        [
            24,
            28
        ],
        [
            24,
            31
        ],
        [
            24,
            25
        ],
        [
            9,
            10
        ],
        [
            9,
            23
        ],
        [
            17,
            21
        ],
        [
            17,
            18
        ],
        [
            25,
            27
        ],
        [
            25,
            26
        ],
        [
            16,
            22
        ],
        [
            16,
            17
        ],
        [
            10,
            12
        ],
        [
            10,
            11
        ],
        [
            2,
            3
        ],
        [
            2,
            9
        ],
        [
            13,
            15
        ],
        [
            13,
            14
        ],
        [
            28,
            30
        ],
        [
            28,
            29
        ],
        [
            3,
            7
        ],
        [
            3,
            8
        ],
        [
            3,
            4
        ],
        [
            18,
            19
        ],
        [
            18,
            20
        ],
        [
            0,
            32
        ],
        [
            0,
            2
        ],
        [
            0,
            1
        ]
    ],
    "candidateNodeList": [
        5,
        7,
        8,
        11,
        14,
        19,
        26,
        29,
        31
    ],
    "cfgEdges": [
        [
            6,
            4
        ],
        [
            20,
            18
        ],
        [
            12,
            10
        ],
        [
            4,
            3
        ],
        [
            24,
            32
        ],
        [
            27,
            25
        ],
        [
            15,
            13
        ],
        [
            17,
            16
        ],
        [
            25,
            30
        ],
        [
            16,
            12
        ],
        [
            10,
            32
        ],
        [
            10,
            27
        ],
        [
            30,
            28
        ],
        [
            13,
            20
        ],
        [
            13,
            12
        ],
        [
            28,
            24
        ],
        [
            3,
            15
        ],
        [
            3,
            10
        ],
        [
            18,
            17
        ],
        [
            0,
            6
        ]
    ],
    "ddgEdges": [
        [
            12,
            32
        ],
        [
            12,
            32
        ],
        [
            12,
            24
        ],
        [
            12,
            10
        ],
        [
            12,
            10
        ],
        [
            24,
            32
        ],
        [
            24,
            32
        ],
        [
            24,
            32
        ],
        [
            24,
            32
        ],
        [
            16,
            32
        ],
        [
            16,
            12
        ],
        [
            16,
            12
        ],
        [
            16,
            24
        ],
        [
            10,
            32
        ],
        [
            10,
            32
        ],
        [
            10,
            32
        ],
        [
            3,
            32
        ],
        [
            3,
            32
        ],
        [
            3,
            32
        ],
        [
            3,
            32
        ],
        [
            3,
            24
        ],
        [
            3,
            24
        ],
        [
            0,
            3
        ],
        [
            0,
            10
        ],
        [
            0,
            16
        ],
        [
            0,
            24
        ]
    ],
    "ncsEdges": [
        [
            1,
            5
        ],
        [
            5,
            6
        ],
        [
            6,
            7
        ],
        [
            7,
            8
        ],
        [
            8,
            11
        ],
        [
            11,
            14
        ],
        [
            14,
            15
        ],
        [
            15,
            19
        ],
        [
            19,
            20
        ],
        [
            20,
            21
        ],
        [
            21,
            22
        ],
        [
            22,
            26
        ],
        [
            26,
            27
        ],
        [
            27,
            29
        ],
        [
            29,
            30
        ],
        [
            30,
            31
        ]
    ],
    "nodeList": {
        "0": "METHOD",
        "1": "PARAM",
        "2": "BLOCK",
        "3": "strlcpy",
        "4": "<operator>.fieldAccess",
        "5": "brcmf_mp_global",
        "6": "FIELD_IDENTIFIER",
        "7": "brcmf_firmware_path",
        "8": "BRCMF_FW_ALTPATH_LEN",
        "9": "CONTROL_STRUCTURE",
        "10": "<operator>.logicalAnd",
        "11": "brcmfmac_pdata",
        "12": "<operator>.logicalAnd",
        "13": "<operator>.indirectFieldAccess",
        "14": "brcmfmac_pdata",
        "15": "FIELD_IDENTIFIER",
        "16": "<operator>.equals",
        "17": "<operator>.indirectIndexAccess",
        "18": "<operator>.fieldAccess",
        "19": "brcmf_mp_global",
        "20": "FIELD_IDENTIFIER",
        "21": "LITERAL",
        "22": "LITERAL",
        "23": "BLOCK",
        "24": "strlcpy",
        "25": "<operator>.fieldAccess",
        "26": "brcmf_mp_global",
        "27": "FIELD_IDENTIFIER",
        "28": "<operator>.indirectFieldAccess",
        "29": "brcmfmac_pdata",
        "30": "FIELD_IDENTIFIER",
        "31": "BRCMF_FW_ALTPATH_LEN",
        "32": "METHOD_RETURN"
    }
}