{
    "Function": "fw_unit_uevent",
    "astEdges": [
        [
            7,
            8
        ],
        [
            5,
            7
        ],
        [
            5,
            6
        ],
        [
            3,
            23
        ],
        [
            3,
            10
        ],
        [
            3,
            5
        ],
        [
            3,
            9
        ],
        [
            3,
            4
        ],
        [
            3,
            15
        ],
        [
            15,
            16
        ],
        [
            15,
            20
        ],
        [
            21,
            22
        ],
        [
            13,
            14
        ],
        [
            20,
            21
        ],
        [
            23,
            24
        ],
        [
            10,
            11
        ],
        [
            10,
            12
        ],
        [
            10,
            13
        ],
        [
            0,
            3
        ],
        [
            0,
            1
        ],
        [
            0,
            25
        ],
        [
            0,
            2
        ],
        [
            16,
            19
        ],
        [
            16,
            18
        ],
        [
            16,
            17
        ]
    ],
    "candidateNodeList": [
        6,
        8,
        11,
        12,
        14,
        17,
        19,
        22
    ],
    "cfgEdges": [
        [
            7,
            5
        ],
        [
            5,
            13
        ],
        [
            21,
            20
        ],
        [
            13,
            10
        ],
        [
            20,
            25
        ],
        [
            23,
            25
        ],
        [
            10,
            16
        ],
        [
            0,
            7
        ],
        [
            16,
            23
        ],
        [
            16,
            21
        ]
    ],
    "ddgEdges": [
        [
            7,
            5
        ],
        [
            7,
            25
        ],
        [
            5,
            10
        ],
        [
            5,
            25
        ],
        [
            21,
            25
        ],
        [
            21,
            25
        ],
        [
            21,
            20
        ],
        [
            20,
            25
        ],
        [
            23,
            25
        ],
        [
            10,
            16
        ],
        [
            10,
            25
        ],
        [
            10,
            25
        ],
        [
            0,
            7
        ],
        [
            0,
            5
        ],
        [
            0,
            23
        ],
        [
            0,
            21
        ],
        [
            0,
            10
        ],
        [
            0,
            13
        ],
        [
            0,
            16
        ],
        [
            16,
            25
        ],
        [
            16,
            25
        ],
        [
            16,
            25
        ]
    ],
    "ncsEdges": [
        [
            1,
            2
        ],
        [
            2,
            4
        ],
        [
            4,
            6
        ],
        [
            6,
            8
        ],
        [
            8,
            9
        ],
        [
            9,
            11
        ],
        [
            11,
            12
        ],
        [
            12,
            14
        ],
        [
            14,
            17
        ],
        [
            17,
            18
        ],
        [
            18,
            19
        ],
        [
            19,
            22
        ],
        [
            22,
            24
        ]
    ],
    "nodeList": {
        "0": "METHOD",
        "1": "PARAM",
        "2": "PARAM",
        "3": "BLOCK",
        "4": "LOCAL",
        "5": "<operator>.assignment",
        "6": "unit",
        "7": "fw_unit",
        "8": "dev",
        "9": "LOCAL",
        "10": "get_modalias",
        "11": "unit",
        "12": "modalias",
        "13": "<operator>.sizeOf",
        "14": "modalias",
        "15": "CONTROL_STRUCTURE",
        "16": "add_uevent_var",
        "17": "env",
        "18": "LITERAL",
        "19": "modalias",
        "20": "RETURN",
        "21": "<operator>.minus",
        "22": "ENOMEM",
        "23": "RETURN",
        "24": "LITERAL",
        "25": "METHOD_RETURN"
    }
}