{
    "Function": "wlc_phy_txpower_ipa_upd",
    "astEdges": [
        [
            27,
            28
        ],
        [
            27,
            33
        ],
        [
            3,
            11
        ],
        [
            3,
            34
        ],
        [
            3,
            4
        ],
        [
            5,
            6
        ],
        [
            5,
            9
        ],
        [
            18,
            19
        ],
        [
            18,
            20
        ],
        [
            6,
            8
        ],
        [
            6,
            7
        ],
        [
            37,
            38
        ],
        [
            37,
            39
        ],
        [
            12,
            16
        ],
        [
            12,
            13
        ],
        [
            2,
            3
        ],
        [
            23,
            27
        ],
        [
            23,
            24
        ],
        [
            36,
            37
        ],
        [
            36,
            40
        ],
        [
            11,
            23
        ],
        [
            11,
            12
        ],
        [
            41,
            42
        ],
        [
            41,
            45
        ],
        [
            17,
            18
        ],
        [
            17,
            21
        ],
        [
            28,
            32
        ],
        [
            28,
            29
        ],
        [
            16,
            17
        ],
        [
            16,
            22
        ],
        [
            42,
            44
        ],
        [
            42,
            43
        ],
        [
            0,
            1
        ],
        [
            0,
            46
        ],
        [
            0,
            2
        ],
        [
            4,
            5
        ],
        [
            4,
            10
        ],
        [
            35,
            36
        ],
        [
            35,
            41
        ],
        [
            29,
            31
        ],
        [
            29,
            30
        ],
        [
            34,
            35
        ],
        [
            13,
            15
        ],
        [
            13,
            14
        ],
        [
            24,
            26
        ],
        [
            24,
            25
        ]
    ],
    "candidateNodeList": [
        7,
        14,
        19,
        25,
        30,
        38,
        40,
        43,
        45
    ],
    "cfgEdges": [
        [
            27,
            23
        ],
        [
            5,
            4
        ],
        [
            18,
            21
        ],
        [
            6,
            9
        ],
        [
            37,
            36
        ],
        [
            12,
            26
        ],
        [
            31,
            29
        ],
        [
            23,
            46
        ],
        [
            39,
            37
        ],
        [
            21,
            17
        ],
        [
            15,
            13
        ],
        [
            36,
            44
        ],
        [
            41,
            46
        ],
        [
            17,
            16
        ],
        [
            28,
            27
        ],
        [
            16,
            12
        ],
        [
            42,
            41
        ],
        [
            0,
            8
        ],
        [
            32,
            28
        ],
        [
            4,
            39
        ],
        [
            4,
            15
        ],
        [
            29,
            32
        ],
        [
            13,
            20
        ],
        [
            9,
            5
        ],
        [
            44,
            42
        ],
        [
            26,
            24
        ],
        [
            20,
            18
        ],
        [
            24,
            31
        ],
        [
            8,
            6
        ]
    ],
    "ddgEdges": [
        [
            27,
            46
        ],
        [
            27,
            23
        ],
        [
            27,
            23
        ],
        [
            12,
            46
        ],
        [
            12,
            46
        ],
        [
            23,
            46
        ],
        [
            23,
            46
        ],
        [
            36,
            46
        ],
        [
            41,
            46
        ],
        [
            41,
            46
        ],
        [
            16,
            46
        ],
        [
            16,
            12
        ],
        [
            16,
            12
        ],
        [
            0,
            27
        ],
        [
            0,
            16
        ],
        [
            0,
            41
        ],
        [
            0,
            36
        ],
        [
            0,
            4
        ],
        [
            4,
            46
        ],
        [
            4,
            46
        ]
    ],
    "ncsEdges": [
        [
            1,
            7
        ],
        [
            7,
            8
        ],
        [
            8,
            9
        ],
        [
            9,
            10
        ],
        [
            10,
            14
        ],
        [
            14,
            15
        ],
        [
            15,
            19
        ],
        [
            19,
            20
        ],
        [
            20,
            21
        ],
        [
            21,
            22
        ],
        [
            22,
            25
        ],
        [
            25,
            26
        ],
        [
            26,
            30
        ],
        [
            30,
            31
        ],
        [
            31,
            32
        ],
        [
            32,
            33
        ],
        [
            33,
            38
        ],
        [
            38,
            39
        ],
        [
            39,
            40
        ],
        [
            40,
            43
        ],
        [
            43,
            44
        ],
        [
            44,
            45
        ]
    ],
    "nodeList": {
        "0": "METHOD",
        "1": "PARAM",
        "2": "BLOCK",
        "3": "CONTROL_STRUCTURE",
        "4": "NREV_GE",
        "5": "<operator>.fieldAccess",
        "6": "<operator>.indirectFieldAccess",
        "7": "pi",
        "8": "FIELD_IDENTIFIER",
        "9": "FIELD_IDENTIFIER",
        "10": "LITERAL",
        "11": "BLOCK",
        "12": "<operator>.assignment",
        "13": "<operator>.indirectFieldAccess",
        "14": "pi",
        "15": "FIELD_IDENTIFIER",
        "16": "<operator>.equals",
        "17": "<operator>.fieldAccess",
        "18": "<operator>.indirectFieldAccess",
        "19": "pi",
        "20": "FIELD_IDENTIFIER",
        "21": "FIELD_IDENTIFIER",
        "22": "LITERAL",
        "23": "<operator>.assignment",
        "24": "<operator>.indirectFieldAccess",
        "25": "pi",
        "26": "FIELD_IDENTIFIER",
        "27": "<operator>.equals",
        "28": "<operator>.fieldAccess",
        "29": "<operator>.indirectFieldAccess",
        "30": "pi",
        "31": "FIELD_IDENTIFIER",
        "32": "FIELD_IDENTIFIER",
        "33": "LITERAL",
        "34": "CONTROL_STRUCTURE",
        "35": "BLOCK",
        "36": "<operator>.assignment",
        "37": "<operator>.indirectFieldAccess",
        "38": "pi",
        "39": "FIELD_IDENTIFIER",
        "40": "false",
        "41": "<operator>.assignment",
        "42": "<operator>.indirectFieldAccess",
        "43": "pi",
        "44": "FIELD_IDENTIFIER",
        "45": "false",
        "46": "METHOD_RETURN"
    }
}