{
    "Function": "firmware_map_add_hotplug",
    "astEdges": [
        [
            58,
            59
        ],
        [
            33,
            34
        ],
        [
            22,
            23
        ],
        [
            22,
            24
        ],
        [
            0,
            4
        ],
        [
            0,
            1
        ],
        [
            0,
            2
        ],
        [
            0,
            70
        ],
        [
            0,
            3
        ],
        [
            27,
            28
        ],
        [
            14,
            15
        ],
        [
            14,
            16
        ],
        [
            48,
            49
        ],
        [
            47,
            48
        ],
        [
            55,
            56
        ],
        [
            55,
            57
        ],
        [
            55,
            58
        ],
        [
            6,
            7
        ],
        [
            6,
            8
        ],
        [
            68,
            69
        ],
        [
            10,
            12
        ],
        [
            10,
            11
        ],
        [
            30,
            31
        ],
        [
            30,
            32
        ],
        [
            45,
            46
        ],
        [
            42,
            43
        ],
        [
            18,
            20
        ],
        [
            18,
            19
        ],
        [
            32,
            35
        ],
        [
            32,
            33
        ],
        [
            37,
            38
        ],
        [
            66,
            67
        ],
        [
            16,
            17
        ],
        [
            44,
            45
        ],
        [
            61,
            62
        ],
        [
            61,
            64
        ],
        [
            61,
            65
        ],
        [
            61,
            63
        ],
        [
            53,
            54
        ],
        [
            20,
            21
        ],
        [
            20,
            22
        ],
        [
            20,
            25
        ],
        [
            29,
            36
        ],
        [
            29,
            30
        ],
        [
            49,
            51
        ],
        [
            49,
            50
        ],
        [
            43,
            44
        ],
        [
            43,
            55
        ],
        [
            43,
            47
        ],
        [
            43,
            52
        ],
        [
            36,
            37
        ],
        [
            36,
            39
        ],
        [
            40,
            41
        ],
        [
            4,
            6
        ],
        [
            4,
            68
        ],
        [
            4,
            61
        ],
        [
            4,
            14
        ],
        [
            4,
            18
        ],
        [
            4,
            66
        ],
        [
            4,
            5
        ],
        [
            4,
            26
        ],
        [
            52,
            53
        ],
        [
            8,
            10
        ],
        [
            8,
            9
        ],
        [
            8,
            13
        ],
        [
            26,
            27
        ],
        [
            26,
            29
        ],
        [
            26,
            42
        ],
        [
            59,
            60
        ],
        [
            39,
            40
        ]
    ],
    "candidateNodeList": [
        7,
        9,
        11,
        13,
        15,
        19,
        21,
        23,
        25,
        28,
        31,
        35,
        38,
        41,
        46,
        50,
        54,
        56,
        60,
        62,
        63,
        64,
        65,
        67
    ],
    "cfgEdges": [
        [
            58,
            55
        ],
        [
            33,
            32
        ],
        [
            22,
            20
        ],
        [
            0,
            10
        ],
        [
            27,
            45
        ],
        [
            27,
            34
        ],
        [
            48,
            47
        ],
        [
            47,
            53
        ],
        [
            55,
            61
        ],
        [
            34,
            33
        ],
        [
            6,
            16
        ],
        [
            6,
            22
        ],
        [
            68,
            70
        ],
        [
            10,
            8
        ],
        [
            30,
            37
        ],
        [
            45,
            44
        ],
        [
            18,
            27
        ],
        [
            32,
            30
        ],
        [
            51,
            49
        ],
        [
            37,
            61
        ],
        [
            37,
            40
        ],
        [
            66,
            68
        ],
        [
            16,
            70
        ],
        [
            44,
            51
        ],
        [
            61,
            66
        ],
        [
            53,
            52
        ],
        [
            20,
            18
        ],
        [
            49,
            48
        ],
        [
            40,
            39
        ],
        [
            52,
            59
        ],
        [
            8,
            6
        ],
        [
            59,
            58
        ],
        [
            39,
            70
        ]
    ],
    "ddgEdges": [
        [
            58,
            70
        ],
        [
            22,
            20
        ],
        [
            22,
            20
        ],
        [
            22,
            61
        ],
        [
            22,
            70
        ],
        [
            0,
            20
        ],
        [
            0,
            66
        ],
        [
            0,
            37
        ],
        [
            0,
            22
        ],
        [
            0,
            30
        ],
        [
            0,
            27
        ],
        [
            0,
            16
        ],
        [
            0,
            55
        ],
        [
            0,
            6
        ],
        [
            0,
            68
        ],
        [
            0,
            40
        ],
        [
            0,
            10
        ],
        [
            0,
            8
        ],
        [
            0,
            61
        ],
        [
            0,
            18
        ],
        [
            0,
            32
        ],
        [
            27,
            55
        ],
        [
            27,
            70
        ],
        [
            47,
            70
        ],
        [
            47,
            70
        ],
        [
            55,
            61
        ],
        [
            55,
            70
        ],
        [
            6,
            70
        ],
        [
            6,
            70
        ],
        [
            68,
            70
        ],
        [
            10,
            22
        ],
        [
            10,
            8
        ],
        [
            10,
            8
        ],
        [
            10,
            70
        ],
        [
            30,
            70
        ],
        [
            30,
            37
        ],
        [
            18,
            27
        ],
        [
            18,
            70
        ],
        [
            32,
            30
        ],
        [
            32,
            70
        ],
        [
            37,
            61
        ],
        [
            37,
            70
        ],
        [
            37,
            70
        ],
        [
            66,
            70
        ],
        [
            66,
            70
        ],
        [
            16,
            70
        ],
        [
            44,
            52
        ],
        [
            44,
            70
        ],
        [
            61,
            66
        ],
        [
            61,
            70
        ],
        [
            61,
            70
        ],
        [
            61,
            70
        ],
        [
            61,
            70
        ],
        [
            20,
            61
        ],
        [
            20,
            61
        ],
        [
            20,
            18
        ],
        [
            20,
            18
        ],
        [
            20,
            18
        ],
        [
            20,
            70
        ],
        [
            20,
            70
        ],
        [
            20,
            70
        ],
        [
            40,
            39
        ],
        [
            40,
            70
        ],
        [
            40,
            70
        ],
        [
            52,
            70
        ],
        [
            52,
            70
        ],
        [
            8,
            6
        ],
        [
            8,
            6
        ],
        [
            8,
            6
        ],
        [
            8,
            20
        ],
        [
            8,
            20
        ],
        [
            8,
            70
        ],
        [
            8,
            70
        ],
        [
            8,
            70
        ],
        [
            39,
            70
        ]
    ],
    "ncsEdges": [
        [
            1,
            2
        ],
        [
            2,
            3
        ],
        [
            3,
            5
        ],
        [
            5,
            7
        ],
        [
            7,
            9
        ],
        [
            9,
            11
        ],
        [
            11,
            12
        ],
        [
            12,
            13
        ],
        [
            13,
            15
        ],
        [
            15,
            17
        ],
        [
            17,
            19
        ],
        [
            19,
            21
        ],
        [
            21,
            23
        ],
        [
            23,
            24
        ],
        [
            24,
            25
        ],
        [
            25,
            28
        ],
        [
            28,
            31
        ],
        [
            31,
            34
        ],
        [
            34,
            35
        ],
        [
            35,
            38
        ],
        [
            38,
            41
        ],
        [
            41,
            46
        ],
        [
            46,
            50
        ],
        [
            50,
            51
        ],
        [
            51,
            54
        ],
        [
            54,
            56
        ],
        [
            56,
            57
        ],
        [
            57,
            60
        ],
        [
            60,
            62
        ],
        [
            62,
            63
        ],
        [
            63,
            64
        ],
        [
            64,
            65
        ],
        [
            65,
            67
        ],
        [
            67,
            69
        ]
    ],
    "nodeList": {
        "0": "METHOD",
        "1": "PARAM",
        "2": "PARAM",
        "3": "PARAM",
        "4": "BLOCK",
        "5": "LOCAL",
        "6": "<operator>.assignment",
        "7": "entry",
        "8": "firmware_map_find_entry",
        "9": "start",
        "10": "<operator>.subtraction",
        "11": "end",
        "12": "LITERAL",
        "13": "type",
        "14": "CONTROL_STRUCTURE",
        "15": "entry",
        "16": "RETURN",
        "17": "LITERAL",
        "18": "<operator>.assignment",
        "19": "entry",
        "20": "firmware_map_find_entry_bootmem",
        "21": "start",
        "22": "<operator>.subtraction",
        "23": "end",
        "24": "LITERAL",
        "25": "type",
        "26": "CONTROL_STRUCTURE",
        "27": "<operator>.logicalNot",
        "28": "entry",
        "29": "BLOCK",
        "30": "<operator>.assignment",
        "31": "entry",
        "32": "kzalloc",
        "33": "<operator>.sizeOf",
        "34": "UNKNOWN",
        "35": "GFP_ATOMIC",
        "36": "CONTROL_STRUCTURE",
        "37": "<operator>.logicalNot",
        "38": "entry",
        "39": "RETURN",
        "40": "<operator>.minus",
        "41": "ENOMEM",
        "42": "CONTROL_STRUCTURE",
        "43": "BLOCK",
        "44": "spin_lock",
        "45": "<operator>.addressOf",
        "46": "map_entries_bootmem_lock",
        "47": "list_del",
        "48": "<operator>.addressOf",
        "49": "<operator>.indirectFieldAccess",
        "50": "entry",
        "51": "FIELD_IDENTIFIER",
        "52": "spin_unlock",
        "53": "<operator>.addressOf",
        "54": "map_entries_bootmem_lock",
        "55": "memset",
        "56": "entry",
        "57": "LITERAL",
        "58": "<operator>.sizeOf",
        "59": "<operator>.indirection",
        "60": "entry",
        "61": "firmware_map_add_entry",
        "62": "start",
        "63": "end",
        "64": "type",
        "65": "entry",
        "66": "add_sysfs_fw_map_entry",
        "67": "entry",
        "68": "RETURN",
        "69": "LITERAL",
        "70": "METHOD_RETURN"
    }
}