{
    "Function": "dmi_save_extended_devices",
    "astEdges": [
        [
            2,
            26
        ],
        [
            2,
            33
        ],
        [
            2,
            10
        ],
        [
            2,
            4
        ],
        [
            2,
            17
        ],
        [
            2,
            3
        ],
        [
            2,
            51
        ],
        [
            2,
            5
        ],
        [
            28,
            29
        ],
        [
            28,
            30
        ],
        [
            30,
            31
        ],
        [
            30,
            32
        ],
        [
            17,
            18
        ],
        [
            17,
            25
        ],
        [
            26,
            27
        ],
        [
            26,
            28
        ],
        [
            11,
            12
        ],
        [
            11,
            15
        ],
        [
            20,
            22
        ],
        [
            20,
            21
        ],
        [
            40,
            42
        ],
        [
            40,
            41
        ],
        [
            7,
            9
        ],
        [
            7,
            8
        ],
        [
            12,
            13
        ],
        [
            12,
            14
        ],
        [
            34,
            36
        ],
        [
            34,
            35
        ],
        [
            5,
            7
        ],
        [
            5,
            6
        ],
        [
            38,
            39
        ],
        [
            38,
            40
        ],
        [
            46,
            48
        ],
        [
            46,
            47
        ],
        [
            18,
            19
        ],
        [
            18,
            24
        ],
        [
            37,
            38
        ],
        [
            33,
            37
        ],
        [
            33,
            50
        ],
        [
            33,
            34
        ],
        [
            33,
            49
        ],
        [
            33,
            46
        ],
        [
            33,
            43
        ],
        [
            52,
            56
        ],
        [
            52,
            53
        ],
        [
            19,
            20
        ],
        [
            19,
            23
        ],
        [
            53,
            54
        ],
        [
            53,
            55
        ],
        [
            51,
            57
        ],
        [
            51,
            52
        ],
        [
            43,
            45
        ],
        [
            43,
            44
        ],
        [
            0,
            2
        ],
        [
            0,
            1
        ],
        [
            0,
            58
        ],
        [
            10,
            11
        ],
        [
            10,
            16
        ]
    ],
    "candidateNodeList": [
        6,
        9,
        13,
        21,
        27,
        29,
        31,
        35,
        41,
        44,
        47,
        49,
        50,
        54,
        57
    ],
    "cfgEdges": [
        [
            28,
            26
        ],
        [
            30,
            28
        ],
        [
            26,
            34
        ],
        [
            11,
            20
        ],
        [
            11,
            16
        ],
        [
            39,
            40
        ],
        [
            14,
            12
        ],
        [
            20,
            19
        ],
        [
            40,
            38
        ],
        [
            7,
            5
        ],
        [
            12,
            11
        ],
        [
            34,
            39
        ],
        [
            5,
            14
        ],
        [
            38,
            37
        ],
        [
            46,
            33
        ],
        [
            16,
            58
        ],
        [
            18,
            30
        ],
        [
            18,
            25
        ],
        [
            37,
            43
        ],
        [
            33,
            53
        ],
        [
            52,
            51
        ],
        [
            19,
            18
        ],
        [
            53,
            52
        ],
        [
            51,
            58
        ],
        [
            43,
            46
        ],
        [
            0,
            8
        ],
        [
            25,
            58
        ],
        [
            8,
            7
        ]
    ],
    "ddgEdges": [
        [
            28,
            38
        ],
        [
            28,
            33
        ],
        [
            28,
            58
        ],
        [
            28,
            58
        ],
        [
            28,
            52
        ],
        [
            28,
            26
        ],
        [
            28,
            26
        ],
        [
            28,
            40
        ],
        [
            26,
            58
        ],
        [
            26,
            33
        ],
        [
            11,
            58
        ],
        [
            11,
            58
        ],
        [
            40,
            58
        ],
        [
            7,
            58
        ],
        [
            7,
            5
        ],
        [
            7,
            28
        ],
        [
            5,
            38
        ],
        [
            5,
            33
        ],
        [
            5,
            58
        ],
        [
            5,
            58
        ],
        [
            5,
            52
        ],
        [
            5,
            19
        ],
        [
            5,
            40
        ],
        [
            5,
            28
        ],
        [
            38,
            58
        ],
        [
            16,
            58
        ],
        [
            18,
            58
        ],
        [
            18,
            58
        ],
        [
            33,
            58
        ],
        [
            33,
            58
        ],
        [
            33,
            58
        ],
        [
            33,
            58
        ],
        [
            33,
            58
        ],
        [
            33,
            58
        ],
        [
            33,
            51
        ],
        [
            52,
            58
        ],
        [
            52,
            51
        ],
        [
            52,
            51
        ],
        [
            19,
            38
        ],
        [
            19,
            33
        ],
        [
            19,
            58
        ],
        [
            19,
            18
        ],
        [
            19,
            18
        ],
        [
            19,
            52
        ],
        [
            19,
            40
        ],
        [
            51,
            58
        ],
        [
            51,
            58
        ],
        [
            51,
            58
        ],
        [
            0,
            38
        ],
        [
            0,
            33
        ],
        [
            0,
            52
        ],
        [
            0,
            19
        ],
        [
            0,
            18
        ],
        [
            0,
            51
        ],
        [
            0,
            11
        ],
        [
            0,
            16
        ],
        [
            0,
            7
        ],
        [
            0,
            28
        ],
        [
            0,
            26
        ],
        [
            0,
            5
        ],
        [
            0,
            40
        ],
        [
            0,
            25
        ],
        [
            25,
            58
        ]
    ],
    "ncsEdges": [
        [
            1,
            3
        ],
        [
            3,
            4
        ],
        [
            4,
            6
        ],
        [
            6,
            8
        ],
        [
            8,
            9
        ],
        [
            9,
            13
        ],
        [
            13,
            14
        ],
        [
            14,
            15
        ],
        [
            15,
            16
        ],
        [
            16,
            21
        ],
        [
            21,
            22
        ],
        [
            22,
            23
        ],
        [
            23,
            24
        ],
        [
            24,
            25
        ],
        [
            25,
            27
        ],
        [
            27,
            29
        ],
        [
            29,
            31
        ],
        [
            31,
            32
        ],
        [
            32,
            35
        ],
        [
            35,
            36
        ],
        [
            36,
            39
        ],
        [
            39,
            41
        ],
        [
            41,
            42
        ],
        [
            42,
            44
        ],
        [
            44,
            45
        ],
        [
            45,
            47
        ],
        [
            47,
            48
        ],
        [
            48,
            49
        ],
        [
            49,
            50
        ],
        [
            50,
            54
        ],
        [
            54,
            55
        ],
        [
            55,
            56
        ],
        [
            56,
            57
        ]
    ],
    "nodeList": {
        "0": "METHOD",
        "1": "PARAM",
        "2": "BLOCK",
        "3": "LOCAL",
        "4": "LOCAL",
        "5": "<operator>.assignment",
        "6": "d",
        "7": "<operator>.cast",
        "8": "UNKNOWN",
        "9": "dm",
        "10": "CONTROL_STRUCTURE",
        "11": "<operator>.lessThan",
        "12": "<operator>.indirectFieldAccess",
        "13": "dm",
        "14": "FIELD_IDENTIFIER",
        "15": "LITERAL",
        "16": "RETURN",
        "17": "CONTROL_STRUCTURE",
        "18": "<operator>.equals",
        "19": "<operator>.and",
        "20": "<operator>.indirectIndexAccess",
        "21": "d",
        "22": "LITERAL",
        "23": "LITERAL",
        "24": "LITERAL",
        "25": "RETURN",
        "26": "<operator>.assignment",
        "27": "name",
        "28": "dmi_string_nosave",
        "29": "dm",
        "30": "<operator>.indirectIndexAccess",
        "31": "d",
        "32": "LITERAL",
        "33": "dmi_save_dev_pciaddr",
        "34": "<operator>.indirectIndexAccess",
        "35": "d",
        "36": "LITERAL",
        "37": "<operator>.indirection",
        "38": "<operator>.cast",
        "39": "UNKNOWN",
        "40": "<operator>.addition",
        "41": "d",
        "42": "LITERAL",
        "43": "<operator>.indirectIndexAccess",
        "44": "d",
        "45": "LITERAL",
        "46": "<operator>.indirectIndexAccess",
        "47": "d",
        "48": "LITERAL",
        "49": "name",
        "50": "DMI_DEV_TYPE_DEV_ONBOARD",
        "51": "dmi_save_one_device",
        "52": "<operator>.and",
        "53": "<operator>.indirectIndexAccess",
        "54": "d",
        "55": "LITERAL",
        "56": "LITERAL",
        "57": "name",
        "58": "METHOD_RETURN"
    }
}